create_multi_langs/__init__.py
create_multi_langs/command_line.py
create_multi_langs/composition/__init__.py
create_multi_langs/composition/csv_reader.py
create_multi_langs/composition/templater.py
create_multi_langs/creater/__init__.py
create_multi_langs/creater/base.py
create_multi_langs/creater/go.py
create_multi_langs/creater/javascript_backend.py
create_multi_langs/creater/javascript_frontend.py
create_multi_langs/creater/python.py
create_multi_langs/creater/python_typing.py
create_multi_langs/creater/typescript_backend.py
create_multi_langs/creater/typescript_frontend.py
tests/__init__.py
tests/test_go.py
tests/test_javascript_backend.py
tests/test_javascript_frontend.py
tests/test_python.py
tests/test_python_typing.py
tests/test_typescript_backend.py
tests/test_typescript_frontend.py
tests/python/__init__.py
tests/python/generated_t.py
tests/python/generated_typing_t.py
Create_Multi_Langs-0.1.1.dist-info/LICENSE
Create_Multi_Langs-0.1.1.dist-info/METADATA
Create_Multi_Langs-0.1.1.dist-info/WHEEL
Create_Multi_Langs-0.1.1.dist-info/entry_points.txt
Create_Multi_Langs-0.1.1.dist-info/top_level.txt
Create_Multi_Langs-0.1.1.dist-info/RECORD
