Metadata-Version: 2.1
Name: Create-Multi-Langs
Version: 0.1.1
Summary: Create-Multi-Langs is a library for creating code file from translated csv file.
Home-page: https://github.com/mychiux413/create-multi-langs
Author: Yihua Chiu
Author-email: mychiux413@gmail.com
License: UNKNOWN
Platform: any
Classifier: Environment :: Web Environment
Classifier: Intended Audience :: Developers
Classifier: License :: OSI Approved :: MIT License
Classifier: Programming Language :: Python :: 3.5
Classifier: Programming Language :: Python :: 3.6
Classifier: Programming Language :: Python :: 3.7
Classifier: Topic :: Internet :: WWW/HTTP :: Dynamic Content
Classifier: Topic :: Software Development :: Code Generators
Classifier: Typing :: Typed
Requires-Python: >=3.5
Requires-Dist: pandas
Requires-Dist: typing
Requires-Dist: jinja2
